dff/__init__.py
dff/client.py
dff/server.py
dff/shm.py
dff_py-0.1.6.dist-info/METADATA
dff_py-0.1.6.dist-info/WHEEL
dff_py-0.1.6.dist-info/top_level.txt
dff_py-0.1.6.dist-info/RECORD
