Metadata-Version: 2.4
Name: dff-py
Version: 0.1.6
Summary: A simple differential fuzzing framework
Author-email: Justin Traglia <jtraglia@pm.me>
License: MIT
Project-URL: Homepage, https://github.com/jtraglia/dff
Project-URL: Repository, https://github.com/jtraglia/dff
Requires-Python: >=3.9
